[
	{
	"id":"01","price":"￥68元","title":"千年木","sales":"216",
	"src":"../images/001plants.jpg",
	"smallSrc":["../images/001plants.jpg"]
	},
	{
	"id":"02","price":"￥258元","title":"小凤梨","sales":"158",
	"src":"../images/002plants.jpg",
	"smallSrc":["../images/002plants.jpg"]
	},
	{
	"id":"03","price":"￥25元","title":"观音莲盆栽","sales":"458",
	"src":"../images/003plants.jpg",
	"smallSrc":["../images/003plants.jpg"]
	},
	{
	"id":"04","price":"￥58元","title":"菖蒲","sales":"38",
	"src":"../images/004plants.jpg",
	"smallSrc":["../images/004plants.jpg"]
	},
	{
	"id":"05","price":"￥68元","title":"白掌","sales":"38",
	"src":"../images/005plants.jpg",
	"smallSrc":["../images/005plants.jpg"]
	},
	{
	"id":"06","price":"￥58元","title":"迷迭香","sales":"99",
	"src":"../images/006plants.jpg",
	"smallSrc":["../images/006plants.jpg"]
	},
	{
	"id":"07","price":"￥38元","title":"绿萝盆栽","sales":"95",
	"src":"../images/007plants.jpg",
	"smallSrc":["../images/007plants.jpg"]
	},
	{
	"id":"08","price":"￥58元","title":"花叶蔓","sales":"125",
	"src":"../images/008plants.jpg",
	"smallSrc":["../images/008plants.jpg"]
	},
	{
	"id":"09","price":"￥66元","title":"四季常青","sales":"158",
	"src":"../images/009plants.jpg",
	"smallSrc":["../images/009plants.jpg"]
	},
	{
	"id":"10","price":"￥66元","title":"小龟背竹","sales":"458",
	"src":"../images/0010plants.jpg",
	"smallSrc":["../images/0010plants.jpg"]
	},
	{
	"id":"11","price":"￥458元","title":"幌伞枫盆栽","sales":"38",
	"src":"../images/0011plants.jpg",
	"smallSrc":["../images/0011plants.jpg"]
	},
	{
	"id":"12","price":"￥558元","title":"双层龙血树绿植","sales":"38",
	"src":"../images/0012plants.jpg",
	"smallSrc":["../images/0012plants.jpg"]
	},
	{
	"id":"13","price":"￥358元","title":"散尾葵","sales":"99",
	"src":"../images/0013plants.jpg",
	"smallSrc":["../images/0013plants.jpg"]
	},
	{
	"id":"14","price":"￥388元","title":"琴叶榕盆栽","sales":"95",
	"src":"../images/0014plants.jpg",
	"smallSrc":["../images/0014plants.jpg"]
	},
	{
	"id":"15","price":"￥358元","title":"鸭脚木","sales":"125",
	"src":"../images/0015plants.jpg",
	"smallSrc":["../images/0015plants.jpg"]
	}
]
